LICENSE
README.md
setup.py
citrix_netscaler_memory_leak.egg-info/PKG-INFO
citrix_netscaler_memory_leak.egg-info/SOURCES.txt
citrix_netscaler_memory_leak.egg-info/dependency_links.txt
citrix_netscaler_memory_leak.egg-info/entry_points.txt
citrix_netscaler_memory_leak.egg-info/requires.txt
citrix_netscaler_memory_leak.egg-info/top_level.txt
citrixnetscalermemoryleak/main.py
citrixnetscalermemoryleak/includes/__init__.py
citrixnetscalermemoryleak/includes/bot.py
citrixnetscalermemoryleak/includes/filereader.py
citrixnetscalermemoryleak/includes/scan.py
citrixnetscalermemoryleak/includes/writefile.py
citrixnetscalermemoryleak/utils/__init__.py
citrixnetscalermemoryleak/utils/configure.py
citrixnetscalermemoryleak/utils/const.py
citrixnetscalermemoryleak/utils/helpers.py
citrixnetscalermemoryleak/utils/status.py